<?xml version="1.0" encoding="utf-8"?>
<nta>
	<name>interaction</name>

	<group id="0" init="true" x="56.0" y="63.0">
		<name>init</name>
		<micro>
			<name>Ask</name>
			<parameter type="array">
				<name>answers robot can recognize</name>
				<item type="string" val="yes" link="human_ready"/>
				<item type="string" val="no" link="human_ignore"/>
				<item type="string" val="maybe" link=""/>
			</parameter>
			<parameter type="str" val="can I do this?">question</parameter>
		</micro>
		<micro>
			<name>Remark</name>
			<parameter type="str" val="this is my result">content</parameter>
			<parameter type="bool" val="false">use_gesture</parameter>
			<parameter type="bool" val="true">Allow_human_to_respond</parameter>
		</micro>
	</group>
	<design>copy</design>
</nta>
